tagbackup/__init__.py
tagbackup/__main__.py
tagbackup/commands/__init__.py
tagbackup/commands/link.py
tagbackup/commands/pull.py
tagbackup/commands/push.py
tagbackup/commands/status.py
tagbackup/commands/unlink.py
tagbackup/constants.py
tagbackup/lib.py
tagbackup/main.py
tagbackup-0.0.9.dist-info/entry_points.txt
tagbackup-0.0.9.dist-info/WHEEL
tagbackup-0.0.9.dist-info/METADATA
tagbackup-0.0.9.dist-info/RECORD
