Metadata-Version: 2.1
Name: tagbackup
Version: 0.0.9
Summary: 
Author: TagBackup
Author-email: hello@tagbackup.com
Requires-Python: >=3.7,<4.0
Classifier: Programming Language :: Python :: 3
Classifier: Programming Language :: Python :: 3.7
Classifier: Programming Language :: Python :: 3.8
Classifier: Programming Language :: Python :: 3.9
Classifier: Programming Language :: Python :: 3.10
Classifier: Programming Language :: Python :: 3.11
Requires-Dist: appdirs (>=1.4.4,<2.0.0)
Requires-Dist: boto3 (>=1.26.48,<2.0.0)
Requires-Dist: humanize (>=4.4.0,<5.0.0)
Requires-Dist: py-machineid (>=0.2.1,<0.3.0)
Requires-Dist: pyyaml (>=6.0,<7.0)
Requires-Dist: requests (>=2.28.1,<3.0.0)
